sortkit/__init__.py
sortkit/bogo_sort.py
sortkit/bubble_sort.py
sortkit/bucket_sort.py
sortkit/comb_sort.py
sortkit/counting_sort.py
sortkit/csv_sort.py
sortkit/exception_handler.py
sortkit/gnome_sort.py
sortkit/heap_sort.py
sortkit/insertion_sort.py
sortkit/makelist.py
sortkit/merge_sort.py
sortkit/quick_sort.py
sortkit/radix_sort.py
sortkit/selection_sort.py
sortkit/shell_sort.py
sortkit/sorting.py
sortkit/string_sort.py
sortkit/tim_sort.py
sortkit-0.1.2.dist-info/LICENSE
sortkit-0.1.2.dist-info/METADATA
sortkit-0.1.2.dist-info/WHEEL
sortkit-0.1.2.dist-info/top_level.txt
sortkit-0.1.2.dist-info/RECORD
