Metadata-Version: 2.1
Name: sortkit
Version: 0.1.2
Summary: A Python library implementing various sorting algorithms
Home-page: https://github.com/Sudipto-tales/sortkit
Author: Sudipta Ghosh
License: MIT
Classifier: Programming Language :: Python :: 3
Classifier: License :: OSI Approved :: MIT License
Classifier: Operating System :: OS Independent
License-File: LICENSE
